color.py
leetcode.py
python_leetcode_runner-1.0.9.dist-info/LICENSE
python_leetcode_runner-1.0.9.dist-info/LICENSE_pre-commit_pre-commit
python_leetcode_runner-1.0.9.dist-info/METADATA
python_leetcode_runner-1.0.9.dist-info/WHEEL
python_leetcode_runner-1.0.9.dist-info/entry_points.txt
python_leetcode_runner-1.0.9.dist-info/top_level.txt
python_leetcode_runner-1.0.9.dist-info/RECORD
