Metadata-Version: 2.1
Name: python-leetcode-runner
Version: 1.0.9
Summary: A CLI app to run any given Leetcode python solution.
Home-page: https://github.com/tusharsadhwani/python_leetcode_runner
Author: Tushar Sadhwani
Author-email: tushar.sadhwani000@gmail.com
License: MIT
Platform: UNKNOWN
Classifier: Programming Language :: Python :: 3
Classifier: License :: OSI Approved :: MIT License
Classifier: Operating System :: OS Independent
Requires-Python: >=3.6
License-File: licenses/LICENSE_pre-commit_pre-commit
License-File: LICENSE
